cdpDumpingUtils/__init__.py
cdpDumpingUtils/main.py
cdpDumpingUtils/version.py
cdpDumpingUtils-0.2.1.dist-info/LICENSE
cdpDumpingUtils-0.2.1.dist-info/METADATA
cdpDumpingUtils-0.2.1.dist-info/WHEEL
cdpDumpingUtils-0.2.1.dist-info/entry_points.txt
cdpDumpingUtils-0.2.1.dist-info/top_level.txt
cdpDumpingUtils-0.2.1.dist-info/RECORD
