Metadata-Version: 2.1
Name: cdpDumpingUtils
Version: 0.2.1
Summary: Download all your courses filles from cahier de prepa
Home-page: https://github.com/Azuxul/cahier-de-prepa-downloader
Author: azuxul
License: GPL-3.0
Classifier: Programming Language :: Python :: 3.0
Classifier: Topic :: Utilities
Classifier: Development Status :: 4 - Beta
Classifier: Environment :: Console
Classifier: License :: OSI Approved :: GNU General Public License v3 (GPLv3)
Requires-Python: >=3.6
License-File: LICENSE
Requires-Dist: setuptools (>=45.0)
Requires-Dist: beautifulsoup4 (>=4.11.2)
Requires-Dist: bs4 (>=0.0.1)
Requires-Dist: html5lib (>=1.1)
Requires-Dist: requests (>=2.22.0)
